{
  "schema_version": "bottom_cache_v1_1",
  "renderer_version": "v0.1.10",
  "generated_at_utc": "2026-02-04T05:10:37.209032Z",
  "as_of_ts": "2026-02-04T13:10:37.209054+08:00",
  "data_commit_sha": "59cfb28d0101067494a0e52f86b2c0f36fe64d16",
  "inputs": {
    "market_cache_stats_path": "market_cache/stats_latest.json",
    "market_cache_ok": true,
    "market_cache_generated_at_utc": "2026-02-04T03:17:44Z",
    "market_cache_as_of_ts": "2026-02-04T03:17:44Z",
    "market_cache_script_version": "market_cache_v2_2_stats_zp_w60_w252_ret1_delta_pctAbs_deltas_dq_lite400",
    "market_cache_ret1_mode": "delta+percent(abs_prev_denominator)",
    "market_cache_percentile_method": "P = count(x<=latest)/n * 100",
    "tw_roll25_report_path": "roll25_cache/latest_report.json",
    "tw_margin_path": "taiwan_margin_cache/latest.json"
  },
  "bottom_state_global": "NONE",
  "triggers_global": {
    "TRIG_PANIC": 0,
    "TRIG_SYSTEMIC_VETO": 0,
    "TRIG_REVERSAL": 0
  },
  "context_global": {
    "context_equity_extreme_sp500_p252_ge_95": 0,
    "sp500_p252": 93.25396825396825
  },
  "distances_global": {
    "vix_panic_gap": 2.0,
    "sp500_ret1_panic_gap": 0.659600025227778,
    "hyg_veto_gap_z": 3.3562288126015662,
    "ofr_veto_gap_z": 1.5432985917443025
  },
  "tw_local_gate": {
    "tw_state": "NONE",
    "UsedDate": "2026-02-03",
    "run_day_tag": "WEEKDAY",
    "used_date_status": "DATA_NOT_UPDATED",
    "lookback_n_actual": 20,
    "lookback_n_target": 20,
    "pct_change": 1.806632,
    "amplitude_pct": 1.758694,
    "turnover_twd": 821574120123.0,
    "close": 32195.36,
    "signals": {
      "DownDay": false,
      "VolumeAmplified": false,
      "VolAmplified": false,
      "NewLow_N": 0,
      "ConsecutiveBreak": 0,
      "stress_newlow": false,
      "paired_basis": false,
      "stress_consecutive_break_raw": false,
      "stress_consecutive_break_paired": false,
      "stress_consec_pair_required": true
    },
    "margin": {
      "data_date": "2026-02-03",
      "unit": "億",
      "flow_signal": "NONE",
      "flow_dbg": {
        "chg_last5_yi": [
          32.8,
          -50.4,
          21.2,
          -31.4,
          21.9
        ],
        "sum_last5_yi": -5.900000000000002,
        "pos_days_last5": 3,
        "rule": "WATCH(sum5>=100.0 & pos_days>=4); ALERT(sum5>=150.0 & pos_days>=4)"
      },
      "level_gate": null,
      "level_dbg": {
        "reason": "insufficient_level_points",
        "min_points": 60,
        "have_points": 30
      },
      "final_signal": "NONE",
      "confidence": "DOWNGRADED",
      "latest_balance_yi": 3821.3,
      "latest_chg_yi": 32.8
    },
    "triggers": {
      "TRIG_TW_PANIC": 0,
      "TRIG_TW_LEVERAGE_HEAT": 0,
      "TRIG_TW_REVERSAL": 0
    },
    "distances": {
      "pct_change_to_nonnegative_gap": 0.0,
      "lookback_missing_points": 0
    }
  },
  "excluded_triggers": [],
  "series_global": {
    "VIX": {
      "series_id": "VIX",
      "risk_dir": "HIGH",
      "latest": {
        "data_date": "2026-02-03",
        "value": 18.0,
        "as_of_ts": "2026-02-04T03:17:44Z",
        "source_url": "https://cdn.cboe.com/api/global/us_indices/daily_prices/VIX_History.csv"
      },
      "w60": {
        "z": 0.38215266770675965,
        "p": 81.66666666666667,
        "ret1_pct": 10.159118727050185,
        "z_delta": 0.6276160512409774,
        "p_delta": 35.00000000000001
      },
      "w252": {
        "z": -0.17697361222612518,
        "p": 60.317460317460316
      },
      "series_signal": "NONE"
    },
    "SP500": {
      "series_id": "SP500",
      "risk_dir": "LOW",
      "latest": {
        "data_date": "2026-02-03",
        "value": 6917.81,
        "as_of_ts": "2026-02-04T03:17:44Z",
        "source_url": "https://stooq.com/q/d/l/?s=^spx&i=d"
      },
      "w60": {
        "z": 0.6864577920575836,
        "p": 71.66666666666667,
        "ret1_pct": -0.840399974772222,
        "z_delta": -0.6018180131172688,
        "p_delta": -23.33333333333333
      },
      "w252": {
        "z": 1.2541317748555567,
        "p": 93.25396825396825
      },
      "series_signal": "NONE"
    },
    "HYG_IEF_RATIO": {
      "series_id": "HYG_IEF_RATIO",
      "risk_dir": "LOW",
      "latest": {
        "data_date": "2026-02-03",
        "value": 0.8448654872814821,
        "as_of_ts": "2026-02-04T03:17:44Z",
        "source_url": "DERIVED"
      },
      "w60": {
        "z": 1.3562288126015662,
        "p": 85.0,
        "ret1_pct": -0.16842626452314302,
        "z_delta": -0.3004331323110192,
        "p_delta": -10.0
      },
      "w252": {
        "z": 0.6945213202644422,
        "p": 76.5873015873016
      },
      "series_signal": "NONE"
    },
    "OFR_FSI": {
      "series_id": "OFR_FSI",
      "risk_dir": "HIGH",
      "latest": {
        "data_date": "2026-01-30",
        "value": -2.255,
        "as_of_ts": "2026-02-04T03:17:44Z",
        "source_url": "https://www.financialresearch.gov/financial-stress-index/data/fsi.csv"
      },
      "w60": {
        "z": 0.45670140825569744,
        "p": 80.0,
        "ret1_pct": 2.169197396963135,
        "z_delta": 0.1667163521009039,
        "p_delta": 6.666666666666671
      },
      "w252": {
        "z": -0.5364763293731907,
        "p": 33.33333333333333
      },
      "series_signal": "NONE"
    }
  },
  "history_audit": {
    "history_load_status": "OK",
    "history_load_reason": "dict.items",
    "loaded_items": 3,
    "backup_status": "OK",
    "backup_reason": "copied_pre_write",
    "backup_path": "dashboard_bottom_cache/history.json.bak.20260204T051037Z.json",
    "backup_bytes": 2828,
    "backup_keep_n": 30,
    "backup_prune": {
      "prune_status": "OK",
      "prune_reason": "within_keep_n:30",
      "deleted": 0
    },
    "history_file_exists": true,
    "history_pre_items": 3,
    "history_pre_unique_days": 3,
    "history_post_items": 3,
    "history_post_unique_days": 3,
    "history_write_status": "OK",
    "history_write_reason": "ok",
    "history_reset": false,
    "history_reset_reason": null,
    "allow_reset": false,
    "allow_shrink": false
  },
  "notes": [
    "Global: single source = market_cache/stats_latest.json",
    "TW: uses existing repo outputs only (no external fetch here)",
    "Signals are deterministic; missing fields => NA + excluded reasons",
    "ret1_pct unit is percent (%)",
    "TW margin heat uses flow signal; optional level gate blocks only when enough data; otherwise downgrade",
    "v0.1.7: always backup history.json before write",
    "v0.1.8: fail-closed history writes + unique-day shrink guard + backup retention",
    "v0.1.9: TW panic hardening (ConsecutiveBreak stress requires pairing)",
    "v0.1.10: report clarity (roll25_raw + roll25_paired_basis)"
  ]
}