{
  "schema_version": "fx_usdtwd_history_v1",
  "items": [
    {
      "date": "2026-01-23",
      "mid": 31.55,
      "spot_buy": 31.475,
      "spot_sell": 31.625,
      "source_url": "https://rate.bot.com.tw/xrt/flcsv/0/L3M/USD/1"
    },
    {
      "date": "2026-01-26",
      "mid": 31.490000000000002,
      "spot_buy": 31.415,
      "spot_sell": 31.565,
      "source_url": "https://rate.bot.com.tw/xrt?Lang=zh-TW",
      "quote_time_local": "2026-01-27T07:31:00+08:00"
    },
    {
      "date": "2026-01-27",
      "mid": 31.43,
      "spot_buy": 31.355,
      "spot_sell": 31.505,
      "source_url": "https://rate.bot.com.tw/xrt?Lang=zh-TW",
      "quote_time_local": "2026-01-27T23:02:00+08:00"
    }
  ]
}