{
  "meta": {
    "run_ts_utc": "2026-03-07T04:04:22.179Z",
    "script_fingerprint": "fetch_tw0050_chip_overlay@2026-02-19.v6",
    "stock_no": "0050",
    "window_n": 5,
    "timeout": 15.0,
    "retries": 3,
    "backoff": 1.5,
    "aligned_last_date": "20260306"
  },
  "sources": {
    "t86_tpl": "https://www.twse.com.tw/fund/T86?response=json&date={ymd}&selectType=ALLBUT0999",
    "twt72u_tpl": "https://www.twse.com.tw/exchangeReport/TWT72U?response=json&date={ymd}&selectType=SLBNLB",
    "pcf_url": "https://www.yuantaetfs.com/tradeInfo/pcf/0050"
  },
  "dq": {
    "flags": [
      "ETF_UNITS_PCF_PARSE_ALL_MISSING",
      "ETF_UNITS_VALUE_MISSING"
    ]
  },
  "data": {
    "borrow_summary": {
      "asof_date": "20260306",
      "borrow_shares": 244241000,
      "borrow_shares_chg_1d": 4487000,
      "borrow_mv_ntd": 18769920850.0,
      "borrow_mv_ntd_chg_1d": 212961250.0
    },
    "etf_units": {
      "source": "yuanta_pcf",
      "source_url": "https://www.yuantaetfs.com/tradeInfo/pcf/0050",
      "trade_date": null,
      "posting_dt": null,
      "units_outstanding": null,
      "units_chg_1d": null,
      "dq": [
        "ETF_UNITS_PCF_POSTING_DATE_NOT_FOUND",
        "ETF_UNITS_PCF_TRADE_DATE_NOT_FOUND",
        "ETF_UNITS_PCF_OUTSTANDING_NOT_FOUND",
        "ETF_UNITS_PCF_NET_CHANGE_NOT_FOUND",
        "ETF_UNITS_PCF_PARSE_ALL_MISSING"
      ]
    },
    "per_day": [
      {
        "date": "20260306",
        "dq": [],
        "sources": {
          "t86": "https://www.twse.com.tw/fund/T86?response=json&date=20260306&selectType=ALLBUT0999",
          "twt72u": "https://www.twse.com.tw/exchangeReport/TWT72U?response=json&date=20260306&selectType=SLBNLB"
        },
        "t86": {
          "dq": [],
          "fields": [
            "證券代號",
            "證券名稱",
            "外陸資買進股數(不含外資自營商)",
            "外陸資賣出股數(不含外資自營商)",
            "外陸資買賣超股數(不含外資自營商)",
            "外資自營商買進股數",
            "外資自營商賣出股數",
            "外資自營商買賣超股數",
            "投信買進股數",
            "投信賣出股數",
            "投信買賣超股數",
            "自營商買賣超股數",
            "自營商買進股數(自行買賣)",
            "自營商賣出股數(自行買賣)",
            "自營商買賣超股數(自行買賣)",
            "自營商買進股數(避險)",
            "自營商賣出股數(避險)",
            "自營商買賣超股數(避險)",
            "三大法人買賣超股數"
          ],
          "raw_row": [
            "0050",
            "元大台灣50      ",
            "3,921,222",
            "79,508,881",
            "-75,587,659",
            "0",
            "0",
            "0",
            "3,300,000",
            "0",
            "3,300,000",
            "-7,362,228",
            "6,668,000",
            "210,000",
            "6,458,000",
            "30,807,002",
            "44,627,230",
            "-13,820,228",
            "-79,649,887"
          ],
          "col_idx": {
            "foreign": 4,
            "trust": 10,
            "dealer": 11,
            "total3": 18
          },
          "foreign_net_shares": -75587659,
          "trust_net_shares": 3300000,
          "dealer_net_shares": -7362228,
          "total3_net_shares": -79649887
        },
        "twt72u": {
          "dq": [],
          "fields": [
            "證券代號",
            "證券名稱",
            "前日借券餘額(1)股",
            "本日異動股借券(2)",
            "本日異動股還券(3)",
            "本日借券餘額股(4)=(1)+(2)-(3)",
            "本日收盤價(5)單位：元",
            "借券餘額市值單位：元(6)=(4)*(5)",
            "市場別"
          ],
          "raw_row": [
            "0050",
            "元大台灣50",
            "239,754,000",
            "4,487,000",
            "0",
            "244,241,000",
            "76.85",
            "18,769,920,850",
            "集中市場"
          ],
          "col_idx": {
            "shares_end": 5,
            "close": 6,
            "mv": 7
          },
          "borrow_shares": 244241000,
          "close": 76.85,
          "borrow_mv_ntd": 18769920850.0
        }
      },
      {
        "date": "20260305",
        "dq": [],
        "sources": {
          "t86": "https://www.twse.com.tw/fund/T86?response=json&date=20260305&selectType=ALLBUT0999",
          "twt72u": "https://www.twse.com.tw/exchangeReport/TWT72U?response=json&date=20260305&selectType=SLBNLB"
        },
        "t86": {
          "dq": [],
          "fields": [
            "證券代號",
            "證券名稱",
            "外陸資買進股數(不含外資自營商)",
            "外陸資賣出股數(不含外資自營商)",
            "外陸資買賣超股數(不含外資自營商)",
            "外資自營商買進股數",
            "外資自營商賣出股數",
            "外資自營商買賣超股數",
            "投信買進股數",
            "投信賣出股數",
            "投信買賣超股數",
            "自營商買賣超股數",
            "自營商買進股數(自行買賣)",
            "自營商賣出股數(自行買賣)",
            "自營商買賣超股數(自行買賣)",
            "自營商買進股數(避險)",
            "自營商賣出股數(避險)",
            "自營商買賣超股數(避險)",
            "三大法人買賣超股數"
          ],
          "raw_row": [
            "0050",
            "元大台灣50      ",
            "11,044,505",
            "87,943,320",
            "-76,898,815",
            "0",
            "0",
            "0",
            "2,300,000",
            "0",
            "2,300,000",
            "-15,702,665",
            "3,366,202",
            "1,558,161",
            "1,808,041",
            "29,869,458",
            "47,380,164",
            "-17,510,706",
            "-90,301,480"
          ],
          "col_idx": {
            "foreign": 4,
            "trust": 10,
            "dealer": 11,
            "total3": 18
          },
          "foreign_net_shares": -76898815,
          "trust_net_shares": 2300000,
          "dealer_net_shares": -15702665,
          "total3_net_shares": -90301480
        },
        "twt72u": {
          "dq": [],
          "fields": [
            "證券代號",
            "證券名稱",
            "前日借券餘額(1)股",
            "本日異動股借券(2)",
            "本日異動股還券(3)",
            "本日借券餘額股(4)=(1)+(2)-(3)",
            "本日收盤價(5)單位：元",
            "借券餘額市值單位：元(6)=(4)*(5)",
            "市場別"
          ],
          "raw_row": [
            "0050",
            "元大台灣50",
            "237,270,000",
            "2,484,000",
            "0",
            "239,754,000",
            "77.40",
            "18,556,959,600",
            "集中市場"
          ],
          "col_idx": {
            "shares_end": 5,
            "close": 6,
            "mv": 7
          },
          "borrow_shares": 239754000,
          "close": 77.4,
          "borrow_mv_ntd": 18556959600.0
        }
      },
      {
        "date": "20260304",
        "dq": [],
        "sources": {
          "t86": "https://www.twse.com.tw/fund/T86?response=json&date=20260304&selectType=ALLBUT0999",
          "twt72u": "https://www.twse.com.tw/exchangeReport/TWT72U?response=json&date=20260304&selectType=SLBNLB"
        },
        "t86": {
          "dq": [],
          "fields": [
            "證券代號",
            "證券名稱",
            "外陸資買進股數(不含外資自營商)",
            "外陸資賣出股數(不含外資自營商)",
            "外陸資買賣超股數(不含外資自營商)",
            "外資自營商買進股數",
            "外資自營商賣出股數",
            "外資自營商買賣超股數",
            "投信買進股數",
            "投信賣出股數",
            "投信買賣超股數",
            "自營商買賣超股數",
            "自營商買進股數(自行買賣)",
            "自營商賣出股數(自行買賣)",
            "自營商買賣超股數(自行買賣)",
            "自營商買進股數(避險)",
            "自營商賣出股數(避險)",
            "自營商買賣超股數(避險)",
            "三大法人買賣超股數"
          ],
          "raw_row": [
            "0050",
            "元大台灣50      ",
            "10,479,060",
            "145,749,029",
            "-135,269,969",
            "0",
            "0",
            "0",
            "4,000,000",
            "85,000",
            "3,915,000",
            "-125,176,070",
            "2,890,000",
            "2,672,827",
            "217,173",
            "72,508,138",
            "197,901,381",
            "-125,393,243",
            "-256,531,039"
          ],
          "col_idx": {
            "foreign": 4,
            "trust": 10,
            "dealer": 11,
            "total3": 18
          },
          "foreign_net_shares": -135269969,
          "trust_net_shares": 3915000,
          "dealer_net_shares": -125176070,
          "total3_net_shares": -256531039
        },
        "twt72u": {
          "dq": [],
          "fields": [
            "證券代號",
            "證券名稱",
            "前日借券餘額(1)股",
            "本日異動股借券(2)",
            "本日異動股還券(3)",
            "本日借券餘額股(4)=(1)+(2)-(3)",
            "本日收盤價(5)單位：元",
            "借券餘額市值單位：元(6)=(4)*(5)",
            "市場別"
          ],
          "raw_row": [
            "0050",
            "元大台灣50",
            "221,489,000",
            "31,070,000",
            "15,289,000",
            "237,270,000",
            "75.60",
            "17,937,612,000",
            "集中市場"
          ],
          "col_idx": {
            "shares_end": 5,
            "close": 6,
            "mv": 7
          },
          "borrow_shares": 237270000,
          "close": 75.6,
          "borrow_mv_ntd": 17937612000.0
        }
      },
      {
        "date": "20260303",
        "dq": [],
        "sources": {
          "t86": "https://www.twse.com.tw/fund/T86?response=json&date=20260303&selectType=ALLBUT0999",
          "twt72u": "https://www.twse.com.tw/exchangeReport/TWT72U?response=json&date=20260303&selectType=SLBNLB"
        },
        "t86": {
          "dq": [],
          "fields": [
            "證券代號",
            "證券名稱",
            "外陸資買進股數(不含外資自營商)",
            "外陸資賣出股數(不含外資自營商)",
            "外陸資買賣超股數(不含外資自營商)",
            "外資自營商買進股數",
            "外資自營商賣出股數",
            "外資自營商買賣超股數",
            "投信買進股數",
            "投信賣出股數",
            "投信買賣超股數",
            "自營商買賣超股數",
            "自營商買進股數(自行買賣)",
            "自營商賣出股數(自行買賣)",
            "自營商買賣超股數(自行買賣)",
            "自營商買進股數(避險)",
            "自營商賣出股數(避險)",
            "自營商買賣超股數(避險)",
            "三大法人買賣超股數"
          ],
          "raw_row": [
            "0050",
            "元大台灣50      ",
            "2,508,722",
            "138,315,090",
            "-135,806,368",
            "0",
            "0",
            "0",
            "1,600,000",
            "243,000",
            "1,357,000",
            "-55,380,909",
            "4,526,000",
            "716,089",
            "3,809,911",
            "46,633,785",
            "105,824,605",
            "-59,190,820",
            "-189,830,277"
          ],
          "col_idx": {
            "foreign": 4,
            "trust": 10,
            "dealer": 11,
            "total3": 18
          },
          "foreign_net_shares": -135806368,
          "trust_net_shares": 1357000,
          "dealer_net_shares": -55380909,
          "total3_net_shares": -189830277
        },
        "twt72u": {
          "dq": [],
          "fields": [
            "證券代號",
            "證券名稱",
            "前日借券餘額(1)股",
            "本日異動股借券(2)",
            "本日異動股還券(3)",
            "本日借券餘額股(4)=(1)+(2)-(3)",
            "本日收盤價(5)單位：元",
            "借券餘額市值單位：元(6)=(4)*(5)",
            "市場別"
          ],
          "raw_row": [
            "0050",
            "元大台灣50",
            "202,470,000",
            "24,309,000",
            "5,290,000",
            "221,489,000",
            "78.75",
            "17,442,258,750",
            "集中市場"
          ],
          "col_idx": {
            "shares_end": 5,
            "close": 6,
            "mv": 7
          },
          "borrow_shares": 221489000,
          "close": 78.75,
          "borrow_mv_ntd": 17442258750.0
        }
      },
      {
        "date": "20260302",
        "dq": [],
        "sources": {
          "t86": "https://www.twse.com.tw/fund/T86?response=json&date=20260302&selectType=ALLBUT0999",
          "twt72u": "https://www.twse.com.tw/exchangeReport/TWT72U?response=json&date=20260302&selectType=SLBNLB"
        },
        "t86": {
          "dq": [],
          "fields": [
            "證券代號",
            "證券名稱",
            "外陸資買進股數(不含外資自營商)",
            "外陸資賣出股數(不含外資自營商)",
            "外陸資買賣超股數(不含外資自營商)",
            "外資自營商買進股數",
            "外資自營商賣出股數",
            "外資自營商買賣超股數",
            "投信買進股數",
            "投信賣出股數",
            "投信買賣超股數",
            "自營商買賣超股數",
            "自營商買進股數(自行買賣)",
            "自營商賣出股數(自行買賣)",
            "自營商買賣超股數(自行買賣)",
            "自營商買進股數(避險)",
            "自營商賣出股數(避險)",
            "自營商買賣超股數(避險)",
            "三大法人買賣超股數"
          ],
          "raw_row": [
            "0050",
            "元大台灣50      ",
            "7,260,307",
            "108,760,405",
            "-101,500,098",
            "0",
            "0",
            "0",
            "3,540,000",
            "326,000",
            "3,214,000",
            "-22,166,179",
            "2,009,851",
            "1,175,000",
            "834,851",
            "30,660,906",
            "53,661,936",
            "-23,001,030",
            "-120,452,277"
          ],
          "col_idx": {
            "foreign": 4,
            "trust": 10,
            "dealer": 11,
            "total3": 18
          },
          "foreign_net_shares": -101500098,
          "trust_net_shares": 3214000,
          "dealer_net_shares": -22166179,
          "total3_net_shares": -120452277
        },
        "twt72u": {
          "dq": [],
          "fields": [
            "證券代號",
            "證券名稱",
            "前日借券餘額(1)股",
            "本日異動股借券(2)",
            "本日異動股還券(3)",
            "本日借券餘額股(4)=(1)+(2)-(3)",
            "本日收盤價(5)單位：元",
            "借券餘額市值單位：元(6)=(4)*(5)",
            "市場別"
          ],
          "raw_row": [
            "0050",
            "元大台灣50",
            "176,611,000",
            "28,680,000",
            "2,821,000",
            "202,470,000",
            "80.35",
            "16,268,464,500",
            "集中市場"
          ],
          "col_idx": {
            "shares_end": 5,
            "close": 6,
            "mv": 7
          },
          "borrow_shares": 202470000,
          "close": 80.35,
          "borrow_mv_ntd": 16268464500.0
        }
      }
    ],
    "t86_agg": {
      "window_n": 5,
      "days_used": [
        "20260302",
        "20260303",
        "20260304",
        "20260305",
        "20260306"
      ],
      "foreign_net_shares_sum": -525062909,
      "trust_net_shares_sum": 14086000,
      "dealer_net_shares_sum": -225788051,
      "total3_net_shares_sum": -736764960
    }
  }
}