{
  "meta": {
    "run_ts_utc": "2026-03-05T01:52:45.120785+00:00",
    "module": "fred_cache",
    "stale_hours": 72.0,
    "stats_generated_at_utc": "2026-03-05T01:51:52+00:00",
    "stats_as_of_ts": "2026-03-05T09:51:50+08:00",
    "script_version": "stats_v1_ddof0_w60_w252_pct_le_ret1_delta",
    "series_count": 13,
    "history_path": "dashboard_fred_cache/history.json",
    "history_lite_path": "cache/history_lite.json",
    "history_lite_used_for_jump": "cache/history_lite.json",
    "jump_calc": "ret1%=(latest-prev)/abs(prev)*100; zΔ60=z60(latest)-z60(prev); pΔ60=p60(latest)-p60(prev) (prev computed from window ending at prev)",
    "signal_rules": "Extreme(abs(Z60)>=2 (WATCH), abs(Z60)>=2.5 (ALERT), P252>=95 or <=5 (INFO), P252<=2 (ALERT)); Jump(2/3 vote: abs(zΔ60)>=0.75, abs(pΔ60)>=15, abs(ret1%)>=2 -> WATCH)",
    "summary": {
      "ALERT": 2,
      "WATCH": 4,
      "INFO": 2,
      "NONE": 5,
      "CHANGED": 5
    },
    "history_lite_series": 13,
    "day_key_local": "2026-03-05",
    "snapshot_id": "commit:cb8301ec9c1965a49a40adc4babbd40ee2f61195",
    "data_commit_sha": "cb8301ec9c1965a49a40adc4babbd40ee2f61195"
  },
  "rows": [
    {
      "series": "DCOILWTICO",
      "dq": "OK",
      "age_hours": 0.014755773611111111,
      "data_date": "2026-03-02",
      "value": 71.13,
      "z60": 2.9252544235327536,
      "z252": 1.8685827015753507,
      "p60": 100.0,
      "p252": 96.82539682539682,
      "z_delta_60": 0.9945851660037646,
      "p_delta_60": 0.0,
      "ret1_pct": 6.227598566308247,
      "reason": "P252>=95;abs(Z60)>=2.5",
      "tag": "EXTREME_Z",
      "near": "NEAR:ZΔ60+NEAR:ret1%",
      "signal_level": "ALERT",
      "prev_signal": "WATCH",
      "delta_signal": "WATCH→ALERT",
      "streak_wa": 0,
      "jump_hits": 2,
      "hitbits": "Z+R",
      "dbg": "p60=100;prev_p60=100;z60=2.925254423533;prev_z60=1.930669257529;prev_v=66.96;last_v=71.13;zΔ60=0.994585166004;pΔ60=0;ret1%=6.227598566308",
      "source_url": "https://api.stlouisfed.org/fred/series/observations?series_id=DCOILWTICO&file_type=json&sort_order=desc&limit=1",
      "effective_as_of_ts": "2026-03-05T09:51:50+08:00"
    },
    {
      "series": "VIXCLS",
      "dq": "OK",
      "age_hours": 0.014755773611111111,
      "data_date": "2026-03-03",
      "value": 23.57,
      "z60": 2.7422064267431234,
      "z252": 0.88917843764433,
      "p60": 100.0,
      "p252": 88.88888888888889,
      "z_delta_60": 0.7297652503634859,
      "p_delta_60": 1.6666666666666714,
      "ret1_pct": 9.934701492537307,
      "reason": "abs(Z60)>=2.5",
      "tag": "EXTREME_Z",
      "near": "NEAR:ZΔ60+NEAR:ret1%",
      "signal_level": "ALERT",
      "prev_signal": "WATCH",
      "delta_signal": "WATCH→ALERT",
      "streak_wa": 0,
      "jump_hits": 1,
      "hitbits": "R",
      "dbg": "p60=100;prev_p60=98.333333333333;z60=2.742206426743;prev_z60=2.01244117638;prev_v=21.44;last_v=23.57;zΔ60=0.729765250363;pΔ60=1.666666666667;ret1%=9.934701492537",
      "source_url": "https://api.stlouisfed.org/fred/series/observations?series_id=VIXCLS&file_type=json&sort_order=desc&limit=1",
      "effective_as_of_ts": "2026-03-05T09:51:50+08:00"
    },
    {
      "series": "BAMLH0A0HYM2",
      "dq": "OK",
      "age_hours": 0.014755773611111111,
      "data_date": "2026-03-03",
      "value": 3.08,
      "z60": 2.0782739346195878,
      "z252": 0.04909643046626579,
      "p60": 96.66666666666667,
      "p252": 66.26984126984127,
      "z_delta_60": 0.3635803833424409,
      "p_delta_60": 0.0,
      "ret1_pct": 1.650165016501659,
      "reason": "abs(Z60)>=2",
      "tag": "EXTREME_Z",
      "near": "NA",
      "signal_level": "WATCH",
      "prev_signal": "WATCH",
      "delta_signal": "SAME",
      "streak_wa": 2,
      "jump_hits": 0,
      "hitbits": "NA",
      "dbg": "NA",
      "source_url": "https://api.stlouisfed.org/fred/series/observations?series_id=BAMLH0A0HYM2&file_type=json&sort_order=desc&limit=1",
      "effective_as_of_ts": "2026-03-05T09:51:50+08:00"
    },
    {
      "series": "SP500",
      "dq": "OK",
      "age_hours": 0.014755773611111111,
      "data_date": "2026-03-04",
      "value": 6869.5,
      "z60": -0.40480075960209494,
      "z252": 0.986610060709369,
      "p60": 31.666666666666668,
      "p252": 82.53968253968254,
      "z_delta_60": 0.924259807451446,
      "p_delta_60": 20.0,
      "ret1_pct": 0.7756031939536089,
      "reason": "abs(zΔ60)>=0.75;abs(pΔ60)>=15",
      "tag": "JUMP_DELTA",
      "near": "NEAR:ZΔ60+NEAR:PΔ60",
      "signal_level": "WATCH",
      "prev_signal": "WATCH",
      "delta_signal": "SAME",
      "streak_wa": 2,
      "jump_hits": 2,
      "hitbits": "Z+P",
      "dbg": "p60=31.666666666667;prev_p60=11.666666666667;z60=-0.404800759602;prev_z60=-1.329060567054;prev_v=6816.63;last_v=6869.5;zΔ60=0.924259807451;pΔ60=20;ret1%=0.775603193954",
      "source_url": "https://api.stlouisfed.org/fred/series/observations?series_id=SP500&file_type=json&sort_order=desc&limit=1",
      "effective_as_of_ts": "2026-03-05T09:51:50+08:00"
    },
    {
      "series": "STLFSI4",
      "dq": "OK",
      "age_hours": 0.014755773611111111,
      "data_date": "2026-02-27",
      "value": -0.4436,
      "z60": 0.43597863433908546,
      "z252": 0.14972486290053,
      "p60": 75.0,
      "p252": 65.87301587301587,
      "z_delta_60": 0.5989673689799295,
      "p_delta_60": 25.0,
      "ret1_pct": 25.831800702223706,
      "reason": "abs(pΔ60)>=15;abs(ret1%)>=2",
      "tag": "JUMP_DELTA",
      "near": "NEAR:PΔ60+NEAR:ret1%",
      "signal_level": "WATCH",
      "prev_signal": "NONE",
      "delta_signal": "NONE→WATCH",
      "streak_wa": 1,
      "jump_hits": 2,
      "hitbits": "P+R",
      "dbg": "p60=75;prev_p60=50;z60=0.435978634339;prev_z60=-0.162988734641;prev_v=-0.5981;last_v=-0.4436;zΔ60=0.59896736898;pΔ60=25;ret1%=25.831800702224",
      "source_url": "https://api.stlouisfed.org/fred/series/observations?series_id=STLFSI4&file_type=json&sort_order=desc&limit=1",
      "effective_as_of_ts": "2026-03-05T09:51:50+08:00"
    },
    {
      "series": "T10Y2Y",
      "dq": "OK",
      "age_hours": 0.014755773611111111,
      "data_date": "2026-03-04",
      "value": 0.55,
      "z60": -2.132040398015123,
      "z252": 0.1062225261801952,
      "p60": 3.3333333333333335,
      "p252": 60.317460317460316,
      "z_delta_60": 0.06415474890483752,
      "p_delta_60": 1.6666666666666667,
      "ret1_pct": 0.0,
      "reason": "abs(Z60)>=2",
      "tag": "EXTREME_Z",
      "near": "NA",
      "signal_level": "WATCH",
      "prev_signal": "WATCH",
      "delta_signal": "SAME",
      "streak_wa": 2,
      "jump_hits": 0,
      "hitbits": "NA",
      "dbg": "NA",
      "source_url": "https://api.stlouisfed.org/fred/series/observations?series_id=T10Y2Y&file_type=json&sort_order=desc&limit=1",
      "effective_as_of_ts": "2026-03-05T09:51:50+08:00"
    },
    {
      "series": "DTWEXBGS",
      "dq": "OK",
      "age_hours": 0.014755773611111111,
      "data_date": "2026-02-27",
      "value": 117.8223,
      "z60": -1.1649468572890498,
      "z252": -1.5271253318580795,
      "p60": 18.333333333333332,
      "p252": 4.365079365079365,
      "z_delta_60": -0.03738621415638166,
      "p_delta_60": -3.3333333333333357,
      "ret1_pct": -0.06946317433984923,
      "reason": "P252<=5",
      "tag": "LONG_EXTREME",
      "near": "NA",
      "signal_level": "INFO",
      "prev_signal": "INFO",
      "delta_signal": "SAME",
      "streak_wa": 0,
      "jump_hits": 0,
      "hitbits": "NA",
      "dbg": "NA",
      "source_url": "https://api.stlouisfed.org/fred/series/observations?series_id=DTWEXBGS&file_type=json&sort_order=desc&limit=1",
      "effective_as_of_ts": "2026-03-05T09:51:50+08:00"
    },
    {
      "series": "NFCINONFINLEVERAGE",
      "dq": "OK",
      "age_hours": 0.014755773611111111,
      "data_date": "2026-02-27",
      "value": -0.4627,
      "z60": 1.636382971069512,
      "z252": 1.5654720036313872,
      "p60": 100.0,
      "p252": 100.0,
      "z_delta_60": 0.008649317232215958,
      "p_delta_60": 0.0,
      "ret1_pct": 0.8804438636704446,
      "reason": "P252>=95",
      "tag": "LONG_EXTREME",
      "near": "NA",
      "signal_level": "INFO",
      "prev_signal": "INFO",
      "delta_signal": "SAME",
      "streak_wa": 0,
      "jump_hits": 0,
      "hitbits": "NA",
      "dbg": "NA",
      "source_url": "https://api.stlouisfed.org/fred/series/observations?series_id=NFCINONFINLEVERAGE&file_type=json&sort_order=desc&limit=1",
      "effective_as_of_ts": "2026-03-05T09:51:50+08:00"
    },
    {
      "series": "DGS10",
      "dq": "OK",
      "age_hours": 0.014755773611111111,
      "data_date": "2026-03-03",
      "value": 4.06,
      "z60": -1.3608363609024645,
      "z252": -1.245691696374501,
      "p60": 15.0,
      "p252": 14.285714285714286,
      "z_delta_60": 0.1342930619311593,
      "p_delta_60": 1.666666666666666,
      "ret1_pct": 0.24691358024690832,
      "reason": "NA",
      "tag": "NA",
      "near": "NA",
      "signal_level": "NONE",
      "prev_signal": "WATCH",
      "delta_signal": "WATCH→NONE",
      "streak_wa": 0,
      "jump_hits": 0,
      "hitbits": "NA",
      "dbg": "NA",
      "source_url": "https://api.stlouisfed.org/fred/series/observations?series_id=DGS10&file_type=json&sort_order=desc&limit=1",
      "effective_as_of_ts": "2026-03-05T09:51:50+08:00"
    },
    {
      "series": "DGS2",
      "dq": "OK",
      "age_hours": 0.014755773611111111,
      "data_date": "2026-03-03",
      "value": 3.51,
      "z60": 0.13360104902632347,
      "z252": -0.9597136269628778,
      "p60": 58.333333333333336,
      "p252": 22.22222222222222,
      "z_delta_60": 0.7224973597357831,
      "p_delta_60": 18.333333333333336,
      "ret1_pct": 1.1527377521613713,
      "reason": "NA",
      "tag": "JUMP_DELTA",
      "near": "NEAR:ZΔ60+NEAR:PΔ60",
      "signal_level": "NONE",
      "prev_signal": "WATCH",
      "delta_signal": "WATCH→NONE",
      "streak_wa": 0,
      "jump_hits": 1,
      "hitbits": "P",
      "dbg": "p60=58.333333333333;prev_p60=40;z60=0.133601049026;prev_z60=-0.588896310709;prev_v=3.47;last_v=3.51;zΔ60=0.722497359736;pΔ60=18.333333333333;ret1%=1.152737752161",
      "source_url": "https://api.stlouisfed.org/fred/series/observations?series_id=DGS2&file_type=json&sort_order=desc&limit=1",
      "effective_as_of_ts": "2026-03-05T09:51:50+08:00"
    },
    {
      "series": "DJIA",
      "dq": "OK",
      "age_hours": 0.014755773611111111,
      "data_date": "2026-03-04",
      "value": 48739.41,
      "z60": -0.35932017220557894,
      "z252": 1.1805859089575144,
      "p60": 36.666666666666664,
      "p252": 84.92063492063492,
      "z_delta_60": 0.3420065024443088,
      "p_delta_60": 5.0,
      "ret1_pct": 0.49099745223167707,
      "reason": "NA",
      "tag": "NA",
      "near": "NA",
      "signal_level": "NONE",
      "prev_signal": "NONE",
      "delta_signal": "SAME",
      "streak_wa": 0,
      "jump_hits": 0,
      "hitbits": "NA",
      "dbg": "NA",
      "source_url": "https://api.stlouisfed.org/fred/series/observations?series_id=DJIA&file_type=json&sort_order=desc&limit=1",
      "effective_as_of_ts": "2026-03-05T09:51:50+08:00"
    },
    {
      "series": "NASDAQCOM",
      "dq": "OK",
      "age_hours": 0.014755773611111111,
      "data_date": "2026-03-03",
      "value": 22516.69,
      "z60": -1.9288146148986869,
      "z252": 0.624959192191936,
      "p60": 1.6666666666666667,
      "p252": 58.333333333333336,
      "z_delta_60": -0.5304742958024873,
      "p_delta_60": -13.333333333333334,
      "ret1_pct": -1.0205786136096573,
      "reason": "NA",
      "tag": "NA",
      "near": "NA",
      "signal_level": "NONE",
      "prev_signal": "NONE",
      "delta_signal": "SAME",
      "streak_wa": 0,
      "jump_hits": 0,
      "hitbits": "NA",
      "dbg": "NA",
      "source_url": "https://api.stlouisfed.org/fred/series/observations?series_id=NASDAQCOM&file_type=json&sort_order=desc&limit=1",
      "effective_as_of_ts": "2026-03-05T09:51:50+08:00"
    },
    {
      "series": "T10Y3M",
      "dq": "OK",
      "age_hours": 0.014755773611111111,
      "data_date": "2026-03-04",
      "value": 0.38,
      "z60": -1.3013076833657886,
      "z252": 1.1158839233869142,
      "p60": 16.666666666666668,
      "p252": 79.76190476190476,
      "z_delta_60": 0.3781470051846818,
      "p_delta_60": 6.666666666666668,
      "ret1_pct": 8.57142857142858,
      "reason": "NA",
      "tag": "JUMP_RET",
      "near": "NEAR:ret1%",
      "signal_level": "NONE",
      "prev_signal": "NONE",
      "delta_signal": "SAME",
      "streak_wa": 0,
      "jump_hits": 1,
      "hitbits": "R",
      "dbg": "p60=16.666666666667;prev_p60=10;z60=-1.301307683366;prev_z60=-1.67945468855;prev_v=0.35;last_v=0.38;zΔ60=0.378147005185;pΔ60=6.666666666667;ret1%=8.571428571429",
      "source_url": "https://api.stlouisfed.org/fred/series/observations?series_id=T10Y3M&file_type=json&sort_order=desc&limit=1",
      "effective_as_of_ts": "2026-03-05T09:51:50+08:00"
    }
  ]
}
